Workbook

Sheet Sales_Transactions
A1: Transaction_ID | B1: Date | C1: Sales_Rep_ID | D1: Customer_ID | E1: Product_ID | F1: Quantity | G1: Unit_Price | H1: Discount | I1: Total_Amount | J1: Region | K1: Payment_Method | L1: Cost_Prices | M1: Profit | N1: Profit_Margin | O1: Month | P1: Quarter | Q1: Year | R1: Day_of_Week | S1: Month_Num | T1: Product_Name | U1: Category | V1: Subcategory | W1: Customer_Segment | X1: Sales_Rep_Name
A2: T10001 | B2: 2023-01-01 | C2: SR1005 | D2: C2014 | E2: P1003 | F2: 17 | G2: 477.48 | H2: 0.1 | I2: 7305.44 | J2: Central | K2: Cash | L2: =VLOOKUP(tblTransactions[[#This Row],[Product_ID]],tblProducts[],5,FALSE) -> 275.51 | M2: =tblTransactions[[#This Row],[Total_Amount]]-(tblTransactions[[#This Row],[Cost_Prices]]*tblTransactions[[#This Row],[Quantity]]*(1-tblTransactions[[#This Row],[Discount]])) -> 3090.137 | N2: =tblTransactions[[#This Row],[Profit]]/tblTransactions[[#This Row],[Total_Amount]] -> 0.42299122 | O2: =TEXT(tblTransactions[[#This Row],[Date]], "MMM-YYYY") -> Jan-2023 | P2: ="Q"&ROUNDUP(MONTH(tblTransactions[[#This Row],[Date]])/3,0)&"-"&YEAR(tblTransactions[[#This Row],[Date]]) -> Q1-2023 | Q2: =YEAR(tblTransactions[[#This Row],[Date]]) -> 2023 | R2: =TEXT(tblTransactions[[#This Row],[Date]],"DDDD") -> Sunday | S2: =MONTH(tblTransactions[[#This Row],[Date]]) -> 1 | T2: =VLOOKUP(E2, Products!$A:$B,2,0) -> Laptops Ele-4 | U2: =VLOOKUP(E2,Products!$A:$C,3,0) -> Electronics | V2: =VLOOKUP(E2,Products!$A:$D,4,0) -> Laptops | W2: =VLOOKUP(D2,Customers!$A:$C,3,0) -> B2B | X2: =VLOOKUP(C2,Sales_Representatives!$A:$B,2,0) -> Jennifer Rodriguez
A3: T10002 | B3: 2023-01-01 | C3: SR1003 | D3: C2014 | E3: P1000 | F3: 12 | G3: 1219.49 | H3: 0.17 | I3: 12146.12 | J3: East | K3: Debit Card | L3: =VLOOKUP(tblTransactions[[#This Row],[Product_ID]],tblProducts[],5,FALSE) -> 686.9 | M3: =tblTransactions[[#This Row],[Total_Amount]]-(tblTransactions[[#This Row],[Cost_Prices]]*tblTransactions[[#This Row],[Quantity]]*(1-tblTransactions[[#This Row],[Discount]])) -> 5304.596 | N3: =tblTransactions[[#This Row],[Profit]]/tblTransactions[[#This Row],[Total_Amount]] -> 0.43673173 | O3: =TEXT(tblTransactions[[#This Row],[Date]], "MMM-YYYY") -> Jan-2023 | P3: ="Q"&ROUNDUP(MONTH(tblTransactions[[#This Row],[Date]])/3,0)&"-"&YEAR(tblTransactions[[#This Row],[Date]]) -> Q1-2023 | Q3: =YEAR(tblTransactions[[#This Row],[Date]]) -> 2023 | R3: =TEXT(tblTransactions[[#This Row],[Date]],"DDDD") -> Sunday | S3: =MONTH(tblTransactions[[#This Row],[Date]]) -> 1 | T3: =VLOOKUP(E3, Products!$A:$B,2,0) -> Laptops Ele-1 | U3: =VLOOKUP(E3,Products!$A:$C,3,0) -> Electronics | V3: =VLOOKUP(E3,Products!$A:$D,4,0) -> Laptops | W3: =VLOOKUP(D3,Customers!$A:$C,3,0) -> B2B | X3: =VLOOKUP(C3,Sales_Representatives!$A:$B,2,0) -> Robert Jones
A4: T10003 | B4: 2023-01-01 | C4: SR1005 | D4: C2049 | E4: P1026 | F4: 17 | G4: 1467.49 | H4: 0.11 | I4: 22203.12 | J4: Central | K4: Cash | L4: =VLOOKUP(tblTransactions[[#This Row],[Product_ID]],tblProducts[],5,FALSE) -> 757.65 | M4: =tblTransactions[[#This Row],[Total_Amount]]-(tblTransactions[[#This Row],[Cost_Prices]]*tblTransactions[[#This Row],[Quantity]]*(1-tblTransactions[[#This Row],[Discount]])) -> 10739.876 | N4: =tblTransactions[[#This Row],[Profit]]/tblTransactions[[#This Row],[Total_Amount]] -> 0.48371019 | O4: =TEXT(tblTransactions[[#This Row],[Date]], "MMM-YYYY") -> Jan-2023 | P4: ="Q"&ROUNDUP(MONTH(tblTransactions[[#This Row],[Date]])/3,0)&"-"&YEAR(tblTransactions[[#This Row],[Date]]) -> Q1-2023 | Q4: =YEAR(tblTransactions[[#This Row],[Date]]) -> 2023 | R4: =TEXT(tblTransactions[[#This Row],[Date]],"DDDD") -> Sunday | S4: =MONTH(tblTransactions[[#This Row],[Date]]) -> 1 | T4: =VLOOKUP(E4, Products!$A:$B,2,0) -> Tables Fur-3 | U4: =VLOOKUP(E4,Products!$A:$C,3,0) -> Furniture | V4: =VLOOKUP(E4,Products!$A:$D,4,0) -> Tables | W4: =VLOOKUP(D4,Customers!$A:$C,3,0) -> B2B | X4: =VLOOKUP(C4,Sales_Representatives!$A:$B,2,0) -> Jennifer Rodriguez
A5: T10004 | B5: 2023-01-01 | C5: SR1015 | D5: C2019 | E5: P1010 | F5: 9 | G5: 1363.46 | H5: 0.12 | I5: 10798.6 | J5: Central | K5: Cash | L5: =VLOOKUP(tblTransactions[[#This Row],[Product_ID]],tblProducts[],5,FALSE) -> 995.41 | M5: =tblTransactions[[#This Row],[Total_Amount]]-(tblTransactions[[#This Row],[Cost_Prices]]*tblTransactions[[#This Row],[Quantity]]*(1-tblTransactions[[#This Row],[Discount]])) -> 2914.9528 | N5: =tblTransactions[[#This Row],[Profit]]/tblTransactions[[#This Row],[Total_Amount]] -> 0.26993803 | O5: =TEXT(tblTransactions[[#This Row],[Date]], "MMM-YYYY") -> Jan-2023 | P5: ="Q"&ROUNDUP(MONTH(tblTransactions[[#This Row],[Date]])/3,0)&"-"&YEAR(tblTransactions[[#This Row],[Date]]) -> Q1-2023 | Q5: =YEAR(tblTransactions[[#This Row],[Date]]) -> 2023 | R5: =TEXT(tblTransactions[[#This Row],[Date]],"DDDD") -> Sunday | S5: =MONTH(tblTransactions[[#This Row],[Date]]) -> 1 | T5: =VLOOKUP(E5, Products!$A:$B,2,0) -> Phones Ele-3 | U5: =VLOOKUP(E5,Products!$A:$C,3,0) -> Electronics | V5: =VLOOKUP(E5,Products!$A:$D,4,0) -> Phones | W5: =VLOOKUP(D5,Customers!$A:$C,3,0) -> B2B | X5: =VLOOKUP(C5,Sales_Representatives!$A:$B,2,0) -> Thomas Lopez
A6: T10005 | B6: 2023-01-01 | C6: SR1014 | D6: C2008 | E6: P1056 | F6: 6 | G6: 322.7 | H6: 0.09 | I6: 1761.94 | J6: West | K6: Credit Card | L6: =VLOOKUP(tblTransactions[[#This Row],[Product_ID]],tblProducts[],5,FALSE) -> 139.81 | M6: =tblTransactions[[#This Row],[Total_Amount]]-(tblTransactions[[#This Row],[Cost_Prices]]*tblTransactions[[#This Row],[Quantity]]*(1-tblTransactions[[#This Row],[Discount]])) -> 998.5774 | N6: =tblTransactions[[#This Row],[Profit]]/tblTransactions[[#This Row],[Total_Amount]] -> 0.56674881 | O6: =TEXT(tblTransactions[[#This Row],[Date]], "MMM-YYYY") -> Jan-2023 | P6: ="Q"&ROUNDUP(MONTH(tblTransactions[[#This Row],[Date]])/3,0)&"-"&YEAR(tblTransactions[[#This Row],[Date]]) -> Q1-2023 | Q6: =YEAR(tblTransactions[[#This Row],[Date]]) -> 2023 | R6: =TEXT(tblTransactions[[#This Row],[Date]],"DDDD") -> Sunday | S6: =MONTH(tblTransactions[[#This Row],[Date]]) -> 1 | T6: =VLOOKUP(E6, Products!$A:$B,2,0) -> Adapters Acc-1 | U6: =VLOOKUP(E6,Products!$A:$C,3,0) -> Accessories | V6: =VLOOKUP(E6,Products!$A:$D,4,0) -> Adapters | W6: =VLOOKUP(D6,Customers!$A:$C,3,0) -> B2C | X6: =VLOOKUP(C6,Sales_Representatives!$A:$B,2,0) -> Thomas Martinez
A7: T10006 | B7: 2023-01-01 | C7: SR1014 | D7: C2032 | E7: P1030 | F7: 30 | G7: 581.47 | H7: 0.16 | I7: 14653.04 | J7: West | K7: Bank Transfer | L7: =VLOOKUP(tblTransactions[[#This Row],[Product_ID]],tblProducts[],5,FALSE) -> 372.07 | M7: =tblTransactions[[#This Row],[Total_Amount]]-(tblTransactions[[#This Row],[Cost_Prices]]*tblTransactions[[#This Row],[Quantity]]*(1-tblTransactions[[#This Row],[Discount]])) -> 5276.876 | N7: =tblTransactions[[#This Row],[Profit]]/tblTransactions[[#This Row],[Total_Amount]] -> 0.36012159 | O7: =TEXT(tblTransactions[[#This Row],[Date]], "MMM-YYYY") -> Jan-2023 | P7: ="Q"&ROUNDUP(MONTH(tblTransactions[[#This Row],[Date]])/3,0)&"-"&YEAR(tblTransactions[[#This Row],[Date]]) -> Q1-2023 | Q7: =YEAR(tblTransactions[[#This Row],[Date]]) -> 2023 | R7: =TEXT(tblTransactions[[#This Row],[Date]],"DDDD") -> Sunday | S7: =MONTH(tblTransactions[[#This Row],[Date]]) -> 1 | T7: =VLOOKUP(E7, Products!$A:$B,2,0) -> Storage Fur-3 | U7: =VLOOKUP(E7,Products!$A:$C,3,0) -> Furniture | V7: =VLOOKUP(E7,Products!$A:$D,4,0) -> Storage | W7: =VLOOKUP(D7,Customers!$A:$C,3,0) -> Enterprise | X7: =VLOOKUP(C7,Sales_Representatives!$A:$B,2,0) -> Thomas Martinez
A8: T10007 | B8: 2023-01-01 | C8: SR1012 | D8: C2012 | E8: P1034 | F8: 2 | G8: 39.32 | H8: 0.05 | I8: 74.71 | J8: South | K8: Debit Card | L8: =VLOOKUP(tblTransactions[[#This Row],[Product_ID]],tblProducts[],5,FALSE) -> 15.81 | M8: =tblTransactions[[#This Row],[Total_Amount]]-(tblTransactions[[#This Row],[Cost_Prices]]*tblTransactions[[#This Row],[Quantity]]*(1-tblTransactions[[#This Row],[Discount]])) -> 44.671 | N8: =tblTransactions[[#This Row],[Profit]]/tblTransactions[[#This Row],[Total_Amount]] -> 0.59792531 | O8: =TEXT(tblTransactions[[#This Row],[Date]], "MMM-YYYY") -> Jan-2023 | P8: ="Q"&ROUNDUP(MONTH(tblTransactions[[#This Row],[Date]])/3,0)&"-"&YEAR(tblTransactions[[#This Row],[Date]]) -> Q1-2023 | Q8: =YEAR(tblTransactions[[#This Row],[Date]]) -> 2023 | R8: =TEXT(tblTransactions[[#This Row],[Date]],"DDDD") -> Sunday | S8: =MONTH(tblTransactions[[#This Row],[Date]]) -> 1 | T8: =VLOOKUP(E8, Products!$A:$B,2,0) -> Paper Off-3 | U8: =VLOOKUP(E8,Products!$A:$C,3,0) -> Office Supplies | V8: =VLOOKUP(E8,Products!$A:$D,4,0) -> Paper | W8: =VLOOKUP(D8,Customers!$A:$C,3,0) -> B2C | X8: =VLOOKUP(C8,Sales_Representatives!$A:$B,2,0) -> Robert Jones
A9: T10008 | B9: 2023-01-02 | C9: SR1012 | D9: C2025 | E9: P1010 | F9: 5 | G9: 1363.46 | H9: 0.01 | I9: 6749.13 | J9: South | K9: PayPal | L9: =VLOOKUP(tblTransactions[[#This Row],[Product_ID]],tblProducts[],5,FALSE) -> 995.41 | M9: =tblTransactions[[#This Row],[Total_Amount]]-(tblTransactions[[#This Row],[Cost_Prices]]*tblTransactions[[#This Row],[Quantity]]*(1-tblTransactions[[#This Row],[Discount]])) -> 1821.8505 | N9: =tblTransactions[[#This Row],[Profit]]/tblTransactions[[#This Row],[Total_Amount]] -> 0.26993857 | O9: =TEXT(tblTransactions[[#This Row],[Date]], "MMM-YYYY") -> Jan-2023 | P9: ="Q"&ROUNDUP(MONTH(tblTransactions[[#This Row],[Date]])/3,0)&"-"&YEAR(tblTransactions[[#This Row],[Date]]) -> Q1-2023 | Q9: =YEAR(tblTransactions[[#This Row],[Date]]) -> 2023 | R9: =TEXT(tblTransactions[[#This Row],[Date]],"DDDD") -> Monday | S9: =MONTH(tblTransactions[[#This Row],[Date]]) -> 1 | T9: =VLOOKUP(E9, Products!$A:$B,2,0) -> Phones Ele-3 | U9: =VLOOKUP(E9,Products!$A:$C,3,0) -> Electronics | V9: =VLOOKUP(E9,Products!$A:$D,4,0) -> Phones | W9: =VLOOKUP(D9,Customers!$A:$C,3,0) -> B2C | X9: =VLOOKUP(C9,Sales_Representatives!$A:$B,2,0) -> Robert Jones
A10: T10009 | B10: 2023-01-02 | C10: SR1014 | D10: C2046 | E10: P1003 | F10: 3 | G10: 477.48 | H10: 0.06 | I10: 1346.49 | J10: West | K10: Debit Card | L10: =VLOOKUP(tblTransactions[[#This Row],[Product_ID]],tblProducts[],5,FALSE) -> 275.51 | M10: =tblTransactions[[#This Row],[Total_Amount]]-(tblTransactions[[#This Row],[Cost_Prices]]*tblTransactions[[#This Row],[Quantity]]*(1-tblTransactions[[#This Row],[Discount]])) -> 569.5518 | N10: =tblTransactions[[#This Row],[Profit]]/tblTransactions[[#This Row],[Total_Amount]] -> 0.42299 | O10: =TEXT(tblTransactions[[#This Row],[Date]], "MMM-YYYY") -> Jan-2023 | P10: ="Q"&ROUNDUP(MONTH(tblTransactions[[#This Row],[Date]])/3,0)&"-"&YEAR(tblTransactions[[#This Row],[Date]]) -> Q1-2023 | Q10: =YEAR(tblTransactions[[#This Row],[Date]]) -> 2023 | R10: =TEXT(tblTransactions[[#This Row],[Date]],"DDDD") -> Monday | S10: =MONTH(tblTransactions[[#This Row],[Date]]) -> 1 | T10: =VLOOKUP(E10, Products!$A:$B,2,0) -> Laptops Ele-4 | U10: =VLOOKUP(E10,Products!$A:$C,3,0) -> Electronics | V10: =VLOOKUP(E10,Products!$A:$D,4,0) -> Laptops | W10: =VLOOKUP(D10,Customers!$A:$C,3,0) -> Small Business | X10: =VLOOKUP(C10,Sales_Representatives!$A:$B,2,0) -> Thomas Martinez
A11: T10010 | B11: 2023-01-02 | C11: SR1003 | D11: C2033 | E11: P1070 | F11: 6 | G11: 2069.22 | H11: 0.07 | I11: 11546.25 | J11: East | K11: PayPal | L11: =VLOOKUP(tblTransactions[[#This Row],[Product_ID]],tblProducts[],5,FALSE) -> 1451.18 | M11: =tblTransactions[[#This Row],[Total_Amount]]-(tblTransactions[[#This Row],[Cost_Prices]]*tblTransactions[[#This Row],[Quantity]]*(1-tblTransactions[[#This Row],[Discount]])) -> 3448.6656 | N11: =tblTransactions[[#This Row],[Profit]]/tblTransactions[[#This Row],[Total_Amount]] -> 0.29868274 | O11: =TEXT(tblTransactions[[#This Row],[Date]], "MMM-YYYY") -> Jan-2023 | P11: ="Q"&ROUNDUP(MONTH(tblTransactions[[#This Row],[Date]])/3,0)&"-"&YEAR(tblTransactions[[#This Row],[Date]]) -> Q1-2023 | Q11: =YEAR(tblTransactions[[#This Row],[Date]]) -> 2023 | R11: =TEXT(tblTransactions[[#This Row],[Date]],"DDDD") -> Monday | S11: =MONTH(tblTransactions[[#This Row],[Date]]) -> 1 | T11: =VLOOKUP(E11, Products!$A:$B,2,0) -> Printers Tec-3 | U11: =VLOOKUP(E11,Products!$A:$C,3,0) -> Technology | V11: =VLOOKUP(E11,Products!$A:$D,4,0) -> Printers | W11: =VLOOKUP(D11,Customers!$A:$C,3,0) -> B2C | X11: =VLOOKUP(C11,Sales_Representatives!$A:$B,2,0) -> Robert Jones
A12: T10011 | B12: 2023-01-03 | C12: SR1004 | D12: C2043 | E12: P1003 | F12: 5 | G12: 477.48 | H12: 0.01 | I12: 2363.53 | J12: West | K12: Cash | L12: =VLOOKUP(tblTransactions[[#This Row],[Product_ID]],tblProducts[],5,FALSE) -> 275.51 | M12: =tblTransactions[[#This Row],[Total_Amount]]-(tblTransactions[[#This Row],[Cost_Prices]]*tblTransactions[[#This Row],[Quantity]]*(1-tblTransactions[[#This Row],[Discount]])) -> 999.7555 | N12: =tblTransactions[[#This Row],[Profit]]/tblTransactions[[#This Row],[Total_Amount]] -> 0.42299252 | O12: =TEXT(tblTransactions[[#This Row],[Date]], "MMM-YYYY") -> Jan-2023 | P12: ="Q"&ROUNDUP(MONTH(tblTransactions[[#This Row],[Date]])/3,0)&"-"&YEAR(tblTransactions[[#This Row],[Date]]) -> Q1-2023 | Q12: =YEAR(tblTransactions[[#This Row],[Date]]) -> 2023 | R12: =TEXT(tblTransactions[[#This Row],[Date]],"DDDD") -> Tuesday | S12: =MONTH(tblTransactions[[#This Row],[Date]]) -> 1 | T12: =VLOOKUP(E12, Products!$A:$B,2,0) -> Laptops Ele-4 | U12: =VLOOKUP(E12,Products!$A:$C,3,0) -> Electronics | V12: =VLOOKUP(E12,Products!$A:$D,4,0) -> Laptops | W12: =VLOOKUP(D12,Customers!$A:$C,3,0) -> Small Business | X12: =VLOOKUP(C12,Sales_Representatives!$A:$B,2,0) -> Thomas Hernandez
A13: T10012 | B13: 2023-01-03 | C13: SR1013 | D13: C2005 | E13: P1039 | F13: 1 | G13: 92.07 | H13: 0.03 | I13: 89.31 | J13: East | K13: Bank Transfer | L13: =VLOOKUP(tblTransactions[[#This Row],[Product_ID]],tblProducts[],5,FALSE) -> 56.98 | M13: =tblTransactions[[#This Row],[Total_Amount]]-(tblTransactions[[#This Row],[Cost_Prices]]*tblTransactions[[#This Row],[Quantity]]*(1-tblTransactions[[#This Row],[Discount]])) -> 34.0394 | N13: =tblTransactions[[#This Row],[Profit]]/tblTransactions[[#This Row],[Total_Amount]] -> 0.38113761 | O13: =TEXT(tblTransactions[[#This Row],[Date]], "MMM-YYYY") -> Jan-2023 | P13: ="Q"&ROUNDUP(MONTH(tblTransactions[[#This Row],[Date]])/3,0)&"-"&YEAR(tblTransactions[[#This Row],[Date]]) -> Q1-2023 | Q13: =YEAR(tblTransactions[[#This Row],[Date]]) -> 2023 | R13: =TEXT(tblTransactions[[#This Row],[Date]],"DDDD") -> Tuesday | S13: =MONTH(tblTransactions[[#This Row],[Date]]) -> 1 | T13: =VLOOKUP(E13, Products!$A:$B,2,0) -> Pens Off-4 | U13: =VLOOKUP(E13,Products!$A:$C,3,0) -> Office Supplies | V13: =VLOOKUP(E13,Products!$A:$D,4,0) -> Pens | W13: =VLOOKUP(D13,Customers!$A:$C,3,0) -> B2C | X13: =VLOOKUP(C13,Sales_Representatives!$A:$B,2,0) -> Sarah Brown
... A3501: T13500 | B3501: 2024-12-30 | C3501: SR1015 | D3501: C2344 | E3501: P1005 | F3501: 1 | G3501: 404.76 | H3501: 0.03 | I3501: 392.62 | J3501: Central | K3501: Debit Card | L3501: =VLOOKUP(tblTransactions[[#This Row],[Product_ID]],tblProducts[],5,FALSE) -> 226.76 | M3501: =tblTransactions[[#This Row],[Total_Amount]]-(tblTransactions[[#This Row],[Cost_Prices]]*tblTransactions[[#This Row],[Quantity]]*(1-tblTransactions[[#This Row],[Discount]])) -> 172.6628 | N3501: =tblTransactions[[#This Row],[Profit]]/tblTransactions[[#This Row],[Total_Amount]] -> 0.43977077 | O3501: =TEXT(tblTransactions[[#This Row],[Date]], "MMM-YYYY") -> Dec-2024 | P3501: ="Q"&ROUNDUP(MONTH(tblTransactions[[#This Row],[Date]])/3,0)&"-"&YEAR(tblTransactions[[#This Row],[Date]]) -> Q4-2024 | Q3501: =YEAR(tblTransactions[[#This Row],[Date]]) -> 2024 | R3501: =TEXT(tblTransactions[[#This Row],[Date]],"DDDD") -> Monday | S3501: =MONTH(tblTransactions[[#This Row],[Date]]) -> 12 | T3501: =VLOOKUP(E3501, Products!$A:$B,2,0) -> Tablets Ele-2 | U3501: =VLOOKUP(E3501,Products!$A:$C,3,0) -> Electronics | V3501: =VLOOKUP(E3501,Products!$A:$D,4,0) -> Tablets | W3501: =VLOOKUP(D3501,Customers!$A:$C,3,0) -> Small Business | X3501: =VLOOKUP(C3501,Sales_Representatives!$A:$B,2,0) -> Thomas Lopez

Sheet Products
A1: Product_ID | B1: Product_Name | C1: Category | D1: Subcategory | E1: Cost_Price | F1: Retail_Price | G1: Supplier
A2: P1000 | B2: Laptops Ele-1 | C2: Electronics | D2: Laptops | E2: 686.9 | F2: 1219.49 | G2: Supplier A
A3: P1001 | B3: Laptops Ele-2 | C3: Electronics | D3: Laptops | E3: 1151.59 | F3: 1841.77 | G3: Supplier A
A4: P1002 | B4: Laptops Ele-3 | C4: Electronics | D4: Laptops | E4: 402.82 | F4: 555.08 | G4: Supplier C
A5: P1003 | B5: Laptops Ele-4 | C5: Electronics | D5: Laptops | E5: 275.51 | F5: 477.48 | G5: Supplier B
A6: P1004 | B6: Tablets Ele-1 | C6: Electronics | D6: Tablets | E6: 981.45 | F6: 1623.35 | G6: Supplier B
A7: P1005 | B7: Tablets Ele-2 | C7: Electronics | D7: Tablets | E7: 226.76 | F7: 404.76 | G7: Supplier B
A8: P1006 | B8: Tablets Ele-3 | C8: Electronics | D8: Tablets | E8: 1282.18 | F8: 1802.96 | G8: Supplier A
A9: P1007 | B9: Tablets Ele-4 | C9: Electronics | D9: Tablets | E9: 436.37 | F9: 607.3 | G9: Supplier E
A10: P1008 | B10: Phones Ele-1 | C10: Electronics | D10: Phones | E10: 595.51 | F10: 930.41 | G10: Supplier A
A11: P1009 | B11: Phones Ele-2 | C11: Electronics | D11: Phones | E11: 761.53 | F11: 1100.88 | G11: Supplier E
A12: P1010 | B12: Phones Ele-3 | C12: Electronics | D12: Phones | E12: 995.41 | F12: 1363.46 | G12: Supplier D
A13: P1011 | B13: Phones Ele-4 | C13: Electronics | D13: Phones | E13: 579.79 | F13: 859.93 | G13: Supplier A
... A76: P1074 | B76: Routers Tec-3 | C76: Technology | D76: Routers | E76: 266.92 | F76: 384.18 | G76: Supplier E

Sheet Sales_Representatives
A1: Sales_Rep_ID | B1: Name | C1: Region | D1: Join_Date | E1: Team | F1: Manager
A2: SR1001 | B2: Jennifer Brown | C2: North | D2: 2018-08-02 | E2: Team A | F2: Manager 1
A3: SR1002 | B3: Michael Davis | C3: South | D3: 2020-12-13 | E3: Team B | F3: Manager 1
A4: SR1003 | B4: Robert Jones | C4: East | D4: 2018-02-05 | E4: Team C | F4: Manager 1
A5: SR1004 | B5: Thomas Hernandez | C5: West | D5: 2018-11-05 | E5: Team D | F5: Manager 1
A6: SR1005 | B6: Jennifer Rodriguez | C6: Central | D6: 2019-01-21 | E6: Team A | F6: Manager 1
A7: SR1006 | B7: Emily Hernandez | C7: North | D7: 2020-01-03 | E7: Team B | F7: Manager 2
A8: SR1007 | B8: Jessica Anderson | C8: South | D8: 2018-01-23 | E8: Team C | F8: Manager 2
A9: SR1008 | B9: Richard Wilson | C9: East | D9: 2021-04-30 | E9: Team D | F9: Manager 2
A10: SR1009 | B10: John Brown | C10: West | D10: 2019-09-19 | E10: Team A | F10: Manager 2
A11: SR1010 | B11: Linda Smith | C11: Central | D11: 2021-06-13 | E11: Team B | F11: Manager 2
A12: SR1011 | B12: Richard Garcia | C12: North | D12: 2018-09-12 | E12: Team C | F12: Manager 3
... A16: SR1015 | B16: Thomas Lopez | C16: Central | D16: 2021-03-14 | E16: Team C | F16: Manager 3

Sheet Customers
A1: Customer_ID | B1: Name | C1: Segment | D1: Location | E1: First_Purchase_Date
A2: C2001 | B2: Jessica Brown | C2: B2C | D2: Austin | E2: 2023-10-07
A3: C2002 | B3: Lisa Miller | C3: B2C | D3: Boston | E3: 2023-04-08
A4: C2003 | B4: Elite Enterprises 3 | C4: Enterprise | D4: Chicago | E4: 2023-08-28
A5: C2004 | B5: David Williams | C5: B2C | D5: Houston | E5: 2023-07-20
A6: C2005 | B6: Jennifer Rodriguez | C6: B2C | D6: Dallas | E6: 2023-11-22
A7: C2006 | B7: David Lopez | C7: B2C | D7: San Jose | E7: 2023-09-16
A8: C2007 | B8: Robert Taylor | C8: B2C | D8: San Jose | E8: 2023-12-12
A9: C2008 | B9: Robert Garcia | C9: B2C | D9: Houston | E9: 2023-05-27
A10: C2009 | B10: Premier LLC 9 | C10: B2B | D10: Dallas | E10: 2023-07-18
A11: C2010 | B11: Lisa Johnson | C11: B2C | D11: Seattle | E11: 2023-05-08
A12: C2011 | B12: Tech Corp 11 | C12: B2B | D12: Denver | E12: 2023-12-26
... A351: C2350 | B351: Advanced Systems 350 | C351: Enterprise | D351: Jacksonville | E351: 2023-03-27

Sheet Targets
A1: Month | B1: Sales_Rep_ID | C1: Target_Amount | D1: Region
A2: 2023-01 | B2: SR1001 | C2: 111819.17
A3: 2023-01 | B3: SR1002 | C3: 77401.46
A4: 2023-01 | B4: SR1003 | C4: 87030.34
A5: 2023-01 | B5: SR1004 | C5: 45837.71
A6: 2023-01 | B6: SR1005 | C6: 55425.49
A7: 2023-01 | B7: SR1006 | C7: 61846.13
A8: 2023-01 | B8: SR1007 | C8: 119059.99
A9: 2023-01 | B9: SR1008 | C9: 68291.64
A10: 2023-01 | B10: SR1009 | C10: 113876.67
A11: 2023-01 | B11: SR1010 | C11: 82670.13
A12: 2023-01 | B12: SR1011 | C12: 73949.43
A13: 2023-01 | B13: SR1012 | C13: 43954.69
... A361: 2024-12 | B361: SR1015 | C361: 111374.81
A362: 2023-01 | C362: 280920.06 | D362: North
A363: 2023-01 | C363: 612172.99 | D363: South
A364: 2023-01 | C364: 624194.35 | D364: East
A365: 2023-01 | C365: 504870.82 | D365: West
A366: 2023-01 | C366: 324210.27 | D366: Central
A367: 2023-02 | C367: 618051.85 | D367: North
A368: 2023-02 | C368: 408602.49 | D368: South
A369: 2023-02 | C369: 396527.58 | D369: East
A370: 2023-02 | C370: 598318.23 | D370: West
A371: 2023-02 | C371: 589363.86 | D371: Central
A372: 2023-03 | C372: 704475.97 | D372: North
A373: 2023-03 | C373: 641960.95 | D373: South
... A481: 2024-12 | C481: 694964.3 | D481: Central

Sheet Rep_Targets
A1: Month | B1: Sales_Rep_ID | C1: Target_Amount
A2: 2023-01 | B2: SR1001 | C2: 111819.17
A3: 2023-01 | B3: SR1002 | C3: 77401.46
A4: 2023-01 | B4: SR1003 | C4: 87030.34
A5: 2023-01 | B5: SR1004 | C5: 45837.71
A6: 2023-01 | B6: SR1005 | C6: 55425.49
A7: 2023-01 | B7: SR1006 | C7: 61846.13
A8: 2023-01 | B8: SR1007 | C8: 119059.99
A9: 2023-01 | B9: SR1008 | C9: 68291.64
A10: 2023-01 | B10: SR1009 | C10: 113876.67
A11: 2023-01 | B11: SR1010 | C11: 82670.13
A12: 2023-01 | B12: SR1011 | C12: 73949.43
A13: 2023-01 | B13: SR1012 | C13: 43954.69
... A361: 2024-12 | B361: SR1015 | C361: 111374.81

Sheet Regional_Targets
A1: Month | B1: Target_Amount | C1: Region
A2: 2023-01 | B2: 280920.06 | C2: North
A3: 2023-01 | B3: 612172.99 | C3: South
A4: 2023-01 | B4: 624194.35 | C4: East
A5: 2023-01 | B5: 504870.82 | C5: West
A6: 2023-01 | B6: 324210.27 | C6: Central
A7: 2023-02 | B7: 618051.85 | C7: North
A8: 2023-02 | B8: 408602.49 | C8: South
A9: 2023-02 | B9: 396527.58 | C9: East
A10: 2023-02 | B10: 598318.23 | C10: West
A11: 2023-02 | B11: 589363.86 | C11: Central
A12: 2023-03 | B12: 704475.97 | C12: North
A13: 2023-03 | B13: 641960.95 | C13: South
... A121: 2024-12 | B121: 694964.3 | C121: Central
